sendlk/__about__.py
sendlk/__init__.py
sendlk/_app.py
sendlk/_client.py
sendlk/_utils.py
sendlk/engine.py
sendlk/exceptions.py
sendlk/options.py
sendlk/responses.py
sendlk-0.2.0.dist-info/LICENSE
sendlk-0.2.0.dist-info/METADATA
sendlk-0.2.0.dist-info/WHEEL
sendlk-0.2.0.dist-info/top_level.txt
sendlk-0.2.0.dist-info/RECORD
