Metadata-Version: 2.1
Name: sendlk
Version: 0.2.0
Summary: Send.lk Python SDK
Home-page: https://github.com/ishangavidusha/sendlk-sdk-python
Download-URL: https://github.com/ishangavidusha/sendlk-sdk-python/archive/refs/tags/v0.2.0.tar.gz
Author: Ishanga Vidusha
Author-email: ishangavidusha@gmail.com
License: MIT License
Keywords: send.lk sms getaway
Classifier: Development Status :: 5 - Production/Stable
Classifier: Intended Audience :: Developers
Classifier: Topic :: Software Development :: Build Tools
Classifier: Programming Language :: Python :: 3
Classifier: Programming Language :: Python :: 3.6
Classifier: Programming Language :: Python :: 3.7
Classifier: Programming Language :: Python :: 3.8
Classifier: Programming Language :: Python :: 3.9
Classifier: Programming Language :: Python :: 3.10
Classifier: License :: OSI Approved :: MIT License
Requires-Python: >=3.6
License-File: LICENSE
Requires-Dist: requests (>=2.26.0)
Requires-Dist: cryptography (>=36.0.1)
